jesse/__init__.py
jesse/config.py
jesse/constants.py
jesse/helpers.py
jesse/info.py
jesse/math_utils.py
jesse/testing_utils.py
jesse/utils.py
jesse/version.py
jesse/controllers/__init__.py
jesse/controllers/auth_controller.py
jesse/controllers/backtest_controller.py
jesse/controllers/candles_controller.py
jesse/controllers/config_controller.py
jesse/controllers/exchange_controller.py
jesse/controllers/file_controller.py
jesse/controllers/live_controller.py
jesse/controllers/lsp_controller.py
jesse/controllers/monte_carlo_controller.py
jesse/controllers/notification_controller.py
jesse/controllers/optimization_controller.py
jesse/controllers/strategy_controller.py
jesse/controllers/system_controller.py
jesse/controllers/websocket_controller.py
jesse/enums/__init__.py
jesse/exceptions/__init__.py
jesse/exchanges/__init__.py
jesse/exchanges/exchange.py
jesse/exchanges/sandbox/Sandbox.py
jesse/exchanges/sandbox/__init__.py
jesse/factories/__init__.py
jesse/factories/candle_factory.py
jesse/factories/order_factory.py
jesse/indicators/__init__.py
jesse/indicators/acosc.py
jesse/indicators/ad.py
jesse/indicators/adosc.py
jesse/indicators/adx.py
jesse/indicators/adxr.py
jesse/indicators/alligator.py
jesse/indicators/alma.py
jesse/indicators/ao.py
jesse/indicators/apo.py
jesse/indicators/aroon.py
jesse/indicators/aroonosc.py
jesse/indicators/atr.py
jesse/indicators/avgprice.py
jesse/indicators/bandpass.py
jesse/indicators/beta.py
jesse/indicators/bollinger_bands.py
jesse/indicators/bollinger_bands_width.py
jesse/indicators/bop.py
jesse/indicators/cc.py
jesse/indicators/cci.py
jesse/indicators/cfo.py
jesse/indicators/cg.py
jesse/indicators/chande.py
jesse/indicators/chop.py
jesse/indicators/cksp.py
jesse/indicators/cmo.py
jesse/indicators/correl.py
jesse/indicators/correlation_cycle.py
jesse/indicators/cvi.py
jesse/indicators/cwma.py
jesse/indicators/damiani_volatmeter.py
jesse/indicators/dec_osc.py
jesse/indicators/decycler.py
jesse/indicators/dema.py
jesse-1.12.2.dist-info/LICENSE
jesse-1.12.2.dist-info/METADATA
jesse-1.12.2.dist-info/WHEEL
jesse-1.12.2.dist-info/entry_points.txt
jesse-1.12.2.dist-info/top_level.txt
jesse-1.12.2.dist-info/RECORD
