Metadata-Version: 2.2
Name: jesse
Version: 1.12.2
Summary: A trading framework for cryptocurrencies
Home-page: https://jesse.trade
Author: Saleh Mir
Author-email: saleh@jesse.trade
Project-URL: Documentation, https://docs.jesse.trade
Project-URL: Say Thanks!, https://jesse.trade/discord
Project-URL: Source, https://github.com/jesse-ai/jesse
Project-URL: Tracker, https://github.com/jesse-ai/jesse/issues
Classifier: Programming Language :: Python :: 3
Classifier: License :: OSI Approved :: MIT License
Classifier: Operating System :: OS Independent
Requires-Python: >=3.10
License-File: LICENSE
Requires-Dist: arrow~=1.2.1
Requires-Dist: blinker~=1.4
Requires-Dist: click~=8.0.3
Requires-Dist: numpy~=1.26.4
Requires-Dist: pandas~=2.2.3
Requires-Dist: peewee~=3.14.8
Requires-Dist: psycopg2-binary~=2.9.9
Requires-Dist: pydash~=6.0.0
Requires-Dist: fnc~=0.5.3
Requires-Dist: pytest~=6.2.5
Requires-Dist: requests~=2.32.0
Requires-Dist: scipy~=1.15.0
Requires-Dist: statsmodels~=0.14.4
Requires-Dist: tabulate~=0.8.9
Requires-Dist: timeloop~=1.0.2
Requires-Dist: websocket-client~=1.8.0
Requires-Dist: wsaccel~=0.6.6
Requires-Dist: simplejson~=3.16.0
Requires-Dist: aioredis~=1.3.1
Requires-Dist: redis~=4.1.4
Requires-Dist: fastapi~=0.111.1
Requires-Dist: uvicorn~=0.29.0
Requires-Dist: websockets>=10.0.0
Requires-Dist: python-dotenv~=0.19.2
Requires-Dist: aiofiles~=0.7.0
Requires-Dist: numba~=0.61.0rc2
Requires-Dist: PyJWT~=2.8.0
Requires-Dist: cryptography~=42.0.5
Requires-Dist: ecdsa>=0.16.0
Requires-Dist: optuna~=4.2.0
Requires-Dist: ray; python_version not in "3.13"
Requires-Dist: eth-account~=0.13.5
Requires-Dist: msgpack~=1.1.0
Requires-Dist: starkbank-ecdsa~=1.1.0
Requires-Dist: jesse-rust==1.0.1
Dynamic: author
Dynamic: author-email
Dynamic: classifier
Dynamic: description
Dynamic: description-content-type
Dynamic: home-page
Dynamic: project-url
Dynamic: requires-dist
Dynamic: requires-python
Dynamic: summary
